opengis/__init__.py
opengis/batch_reprojection_tool.py
opengis/modis_reprojection_tool.py
opengis/mosaic.py
opengis-3.1.6.dist-info/METADATA
opengis-3.1.6.dist-info/WHEEL
opengis-3.1.6.dist-info/licenses/LICENSE.txt
opengis-3.1.6.dist-info/RECORD
