Metadata-Version: 2.3
Name: opengis
Version: 3.1.6
Summary: An open source GIS tool.
Project-URL: Homepage, https://github.com/caaszj/opengis
Project-URL: Bug Tracker, https://github.com/caaszj/opengis/issues
Author-email: Zijie Wang <773598627@qq.com>
Classifier: License :: OSI Approved :: MIT License
Classifier: Natural Language :: English
Classifier: Programming Language :: Python :: 3
Classifier: Topic :: Scientific/Engineering :: GIS
Requires-Python: >=3.9
Requires-Dist: gdal
Requires-Dist: geopandas
Requires-Dist: numpy
Requires-Dist: rasterio
Requires-Dist: rasterstats
Requires-Dist: shapely
Requires-Dist: tqdm
